JsonDB/__init__.py
JsonDB/example.py
JsonDB/jsonDB.py
tests/__init__.py
tests/test.py
JsonDB_labm1997-0.0.3.post1.dist-info/LICENSE
JsonDB_labm1997-0.0.3.post1.dist-info/METADATA
JsonDB_labm1997-0.0.3.post1.dist-info/WHEEL
JsonDB_labm1997-0.0.3.post1.dist-info/top_level.txt
JsonDB_labm1997-0.0.3.post1.dist-info/RECORD
