Metadata-Version: 2.1
Name: JsonDB-labm1997
Version: 0.0.3.post1
Summary: This is a simple I/O JSON handler that allows direct operations on JSONs and with a single call to `JsonDB.flushAll`you can save them all on permanent memory.
Home-page: https://gitlab.com/unball/jsondb
Author: Luiz Antônio Borges Martins
Author-email: labm1997@gmail.com
License: UNKNOWN
Platform: UNKNOWN
Classifier: Programming Language :: Python :: 3
Classifier: License :: OSI Approved :: GNU General Public License v3 (GPLv3)
Classifier: Operating System :: OS Independent
Requires-Python: >=3.6
